kloudless/__init__.py
kloudless/account.py
kloudless/application.py
kloudless/auth.py
kloudless/client.py
kloudless/config.py
kloudless/exceptions.py
kloudless/re_patterns.py
kloudless/util.py
kloudless/version.py
kloudless/resources/__init__.py
kloudless/resources/base.py
kloudless-2.0.1.dist-info/LICENSE
kloudless-2.0.1.dist-info/METADATA
kloudless-2.0.1.dist-info/WHEEL
kloudless-2.0.1.dist-info/top_level.txt
kloudless-2.0.1.dist-info/RECORD
