Metadata-Version: 2.1
Name: kloudless
Version: 2.0.1
Summary: Python library for the Kloudless API
Home-page: https://github.com/kloudless/kloudless-python/
Author: Kloudless
Author-email: hello@kloudless.com
License: MIT
Platform: UNKNOWN
Classifier: Programming Language :: Python
Classifier: Intended Audience :: Developers
Classifier: Natural Language :: English
Classifier: License :: OSI Approved :: MIT License
Classifier: Programming Language :: Python :: 2.7
Classifier: Programming Language :: Python :: 3.5
Classifier: Programming Language :: Python :: 3.6
Classifier: Programming Language :: Python :: 3.7
Requires-Dist: requests (>=1.0)
Requires-Dist: python-dateutil
Requires-Dist: six
